ktrain/__init__.py
ktrain/core.py
ktrain/dataset.py
ktrain/imports.py
ktrain/models.py
ktrain/predictor.py
ktrain/preprocessor.py
ktrain/torch_base.py
ktrain/utils.py
ktrain/version.py
ktrain/graph/__init__.py
ktrain/graph/data.py
ktrain/graph/learner.py
ktrain/graph/models.py
ktrain/graph/predictor.py
ktrain/graph/preprocessor.py
ktrain/graph/sg_wrappers.py
ktrain/lroptimize/__init__.py
ktrain/lroptimize/lrfinder.py
ktrain/lroptimize/optimization.py
ktrain/lroptimize/sgdr.py
ktrain/lroptimize/triangular.py
ktrain/tabular/__init__.py
ktrain/tabular/causalinference.py
ktrain/tabular/data.py
ktrain/tabular/dataset.py
ktrain/tabular/models.py
ktrain/tabular/predictor.py
ktrain/tabular/preprocessor.py
ktrain/text/__init__.py
ktrain/text/data.py
ktrain/text/dataset.py
ktrain/text/eda.py
ktrain/text/learner.py
ktrain/text/models.py
ktrain/text/predictor.py
ktrain/text/preprocessor.py
ktrain/text/stopwords-zh.txt
ktrain/text/textextractor.py
ktrain/text/textutils.py
ktrain/text/kw/__init__.py
ktrain/text/kw/core.py
ktrain/text/ner/__init__.py
ktrain/text/ner/data.py
ktrain/text/ner/dataset.py
ktrain/text/ner/learner.py
ktrain/text/ner/metrics.py
ktrain/text/ner/models.py
ktrain/text/ner/predictor.py
ktrain/text/ner/preprocessor.py
ktrain/text/ner/anago/__init__.py
ktrain/text/ner/anago/callbacks.py
ktrain/text/ner/anago/layers.py
ktrain/text/ner/anago/layers_standalone.py
ktrain/text/ner/anago/models.py
ktrain/text/ner/anago/preprocessing.py
ktrain/text/ner/anago/tagger.py
ktrain/text/ner/anago/trainer.py
ktrain/text/ner/anago/utils.py
ktrain/text/ner/anago/wrapper.py
ktrain/text/qa/__init__.py
ktrain/text/qa/core.py
ktrain/text/qa/qa_finetuner.py
ktrain/text/shallownlp/__init__.py
ktrain/text/shallownlp/classifier.py
ktrain/text/shallownlp/imports.py
ktrain/text/shallownlp/ner.py
ktrain/text/shallownlp/searcher.py
ktrain/text/shallownlp/utils.py
ktrain/text/shallownlp/ner_models/ner_chinese
ktrain/text/shallownlp/ner_models/ner_chinese.preproc
ktrain-0.31.2.dist-info/LICENSE
ktrain-0.31.2.dist-info/METADATA
ktrain-0.31.2.dist-info/WHEEL
ktrain-0.31.2.dist-info/top_level.txt
ktrain-0.31.2.dist-info/RECORD
