Metadata-Version: 2.1
Name: ktrain
Version: 0.31.2
Summary: ktrain is a wrapper for TensorFlow Keras that makes deep learning and AI more accessible and easier to apply
Home-page: https://github.com/amaiya/ktrain
Author: Arun S. Maiya
Author-email: arun@maiya.net
License: Apache License 2.0
Keywords: tensorflow,keras,deep learning,machine learning
Platform: UNKNOWN
Classifier: Development Status :: 4 - Beta
Classifier: Intended Audience :: Developers
Classifier: Topic :: Scientific/Engineering :: Artificial Intelligence
Classifier: License :: OSI Approved :: Apache Software License
Classifier: Programming Language :: Python :: 3.6
Classifier: Programming Language :: Python :: 3.7
Classifier: Programming Language :: Python :: 3.8
Classifier: Programming Language :: Python :: 3.9
License-File: LICENSE
Requires-Dist: scikit-learn (==0.24.2)
Requires-Dist: matplotlib (>=3.0.0)
Requires-Dist: pandas (>=1.0.1)
Requires-Dist: fastprogress (>=0.1.21)
Requires-Dist: requests
Requires-Dist: joblib
Requires-Dist: packaging
Requires-Dist: langdetect
Requires-Dist: jieba
Requires-Dist: cchardet
Requires-Dist: chardet
Requires-Dist: syntok (==1.3.3)
Requires-Dist: transformers (==4.10.3)
Requires-Dist: sentencepiece
Requires-Dist: keras-bert (>=0.86.0)
Requires-Dist: whoosh
Provides-Extra: all
Requires-Dist: ipython ; extra == 'all'
Requires-Dist: datasets ; extra == 'all'
Requires-Dist: textblob ; extra == 'all'
Requires-Dist: tika ; extra == 'all'
Requires-Dist: textract ; extra == 'all'
Requires-Dist: causalnlp ; extra == 'all'
Requires-Dist: librosa ; extra == 'all'
Requires-Dist: torch (==1.8.1) ; extra == 'all'
Requires-Dist: shap ; extra == 'all'
Provides-Extra: tests
Requires-Dist: ipython ; extra == 'tests'
Requires-Dist: datasets ; extra == 'tests'
Requires-Dist: textblob ; extra == 'tests'
Requires-Dist: tika ; extra == 'tests'
Requires-Dist: textract ; extra == 'tests'
Requires-Dist: causalnlp ; extra == 'tests'
Requires-Dist: librosa ; extra == 'tests'
Requires-Dist: torch (==1.8.1) ; extra == 'tests'
Requires-Dist: shap ; extra == 'tests'
